alexlib/__init__.py
alexlib/deeplearning.py
alexlib/deeplearning_torch.py
alexlib/history.py
alexlib/miscellaneous.py
alexlib/toolbox.py
alexlib-1.9.0.dist-info/METADATA
alexlib-1.9.0.dist-info/WHEEL
alexlib-1.9.0.dist-info/top_level.txt
alexlib-1.9.0.dist-info/RECORD
