Metadata-Version: 2.1
Name: alexlib
Version: 1.9.0
Summary: Making Python even more convenient by extending list and dict and pathlib and more.
Home-page: https://github.com/thisismygitrepo/alexlib
Author: Alex Al-Saffar
Author-email: programmer@usa.com
License: Apache 2.0
Platform: UNKNOWN
